data_structures_Mht/__init__.py
data_structures_Mht/array.py
data_structures_Mht/linked_list.py
data_structures_Mht/queue.py
data_structures_Mht/stack.py
data_structures_Mht/tree.py
python_data_structures_bootcamp-0.1.3.dist-info/licenses/LICENSE
python_data_structures_bootcamp-0.1.3.dist-info/METADATA
python_data_structures_bootcamp-0.1.3.dist-info/WHEEL
python_data_structures_bootcamp-0.1.3.dist-info/top_level.txt
python_data_structures_bootcamp-0.1.3.dist-info/RECORD
