Metadata-Version: 2.4
Name: python_data-structures_bootcamp
Version: 0.1.3
Summary: This is my first try in building package
Home-page: https://mahamat19.github.io/Mahamat_Data_Struct_Rep
Author: Mahamat Assouna
Author-email: amahamat@aimsammi.org
License: MIT
Classifier: Programming Language :: Python :: 3
Classifier: Operating System :: OS Independent
Requires-Python: >=3.6
License-File: LICENSE
Dynamic: author
Dynamic: author-email
Dynamic: classifier
Dynamic: description
Dynamic: description-content-type
Dynamic: home-page
Dynamic: license
Dynamic: license-file
Dynamic: requires-python
Dynamic: summary
